MANIFEST.in
README.md
setup.cfg
setup.py
django_molly.egg-info/PKG-INFO
django_molly.egg-info/SOURCES.txt
django_molly.egg-info/dependency_links.txt
django_molly.egg-info/requires.txt
django_molly.egg-info/top_level.txt
molly/__init__.py
molly/apps.py
molly/models.py
molly/signals.py
molly/test.py