Metadata-Version: 1.1
Name: django-molly
Version: 0.0.2
Summary: `molly`.
Home-page: https://github.com/anthonyalmarza/molly
Author: Anthony
Author-email: UNKNOWN
License: UNKNOWN
Keywords: molly
Platform: UNKNOWN
Classifier: Intended Audience :: Developers
Classifier: Natural Language :: English
Classifier: Operating System :: OS Independent
Classifier: Programming Language :: Python
